pyflat/__init__.py
pyflat/pyflat.py
pyflat-0.2.1.dist-info/METADATA
pyflat-0.2.1.dist-info/WHEEL
pyflat-0.2.1.dist-info/top_level.txt
pyflat-0.2.1.dist-info/RECORD
