Metadata-Version: 2.1
Name: pyflat
Version: 0.2.1
Summary: Python library to transform objects into positional flat string lines
Home-page: https://github.com/risparfinance/pyflat
Author: Rafael Izidoro
Author-email: izidoro.rafa@gmail.com
License: MIT
Platform: UNKNOWN
Classifier: Development Status :: 3 - Alpha
Classifier: Intended Audience :: Customer Service
Classifier: Intended Audience :: Financial and Insurance Industry
Classifier: License :: OSI Approved :: MIT License
Classifier: Operating System :: OS Independent
Classifier: Programming Language :: Python :: 3.6
Classifier: Programming Language :: Python :: 3.7
Classifier: Programming Language :: Python :: 3.8
